dnac_pnp/__init__.py
dnac_pnp/__version__.py
dnac_pnp/api_call_handler.py
dnac_pnp/api_endpoint_handler.py
dnac_pnp/app.py
dnac_pnp/compatible_dnac_packages.json
dnac_pnp/config_handler.py
dnac_pnp/device_claim_handler.py
dnac_pnp/device_delete_handler.py
dnac_pnp/device_import_handler.py
dnac_pnp/dnac_handler.py
dnac_pnp/dnac_info_butler.py
dnac_pnp/dnac_info_handler.py
dnac_pnp/dnac_params.py
dnac_pnp/dnac_token_generator.py
dnac_pnp/endpoints.json
dnac_pnp/header_handler.py
dnac_pnp/site_handler.py
dnac_pnp/utils.py
dnac_pnp-1.0.2b1.dist-info/AUTHORS.rst
dnac_pnp-1.0.2b1.dist-info/LICENSE
dnac_pnp-1.0.2b1.dist-info/METADATA
dnac_pnp-1.0.2b1.dist-info/WHEEL
dnac_pnp-1.0.2b1.dist-info/entry_points.txt
dnac_pnp-1.0.2b1.dist-info/top_level.txt
dnac_pnp-1.0.2b1.dist-info/RECORD
