Metadata-Version: 2.1
Name: dnac-pnp
Version: 1.0.2b1
Summary: Cisco DNA center PnP device add, claim and delete automation
Home-page: https://github.com/nttde/dnac_pnp.git
Author: Dalwar Hossain
Author-email: dalwar.hossain@global.ntt
Maintainer: NTT Germany Network Automation Development Team
Maintainer-email: DE.PS.DI.Automation@global.ntt
License: BSD-3-Clause License
Keywords: dnac,pnp,cisco,NTT
Platform: UNKNOWN
Classifier: Development Status :: 4 - Beta
Classifier: Intended Audience :: Developers
Classifier: Natural Language :: English
Classifier: Programming Language :: Python :: 3.6
Classifier: Programming Language :: Python :: 3.7
Classifier: Programming Language :: Python :: 3.8
Classifier: Programming Language :: Python :: 3 :: Only
Requires-Python: >=3.6
Requires-Dist: click (>=7.0)
Requires-Dist: requests (>=2.22.0)
Requires-Dist: colorama (>=0.4.1)
Requires-Dist: pyyaml (>=5.1.1)
Requires-Dist: tabulate (>=0.8.3)
Requires-Dist: netmiko (>=2.4.1)
Requires-Dist: tqdm (>=4.36.1)
